{
    "data": {
        "normal": {
            "history": {
                "2022-11-19": {
                    "avg": 108.315,
                    "count": 2,
                    "min": 93.72,
                    "max": 122.91
                },
                "2022-11-21": {
                    "avg": 35,
                    "count": 1,
                    "min": 35,
                    "max": 35
                },
                "2022-11-23": {
                    "avg": 60.55,
                    "count": 1,
                    "min": 60.55,
                    "max": 60.55
                },
                "2022-11-24": {
                    "avg": 163,
                    "count": 1,
                    "min": 163,
                    "max": 163
                },
                "2022-11-27": {
                    "avg": 133.2,
                    "count": 1,
                    "min": 133.2,
                    "max": 133.2
                },
                "2022-12-03": {
                    "avg": 100.37,
                    "count": 1,
                    "min": 100.37,
                    "max": 100.37
                },
                "2022-12-05": {
                    "avg": 96.64500000000001,
                    "count": 2,
                    "min": 62.1,
                    "max": 131.19
                },
                "2022-12-06": {
                    "avg": 59.94,
                    "count": 1,
                    "min": 59.94,
                    "max": 59.94
                },
                "2022-12-13": {
                    "avg": 242.17,
                    "count": 2,
                    "min": 92.69,
                    "max": 391.65
                },
                "2022-12-16": {
                    "avg": 30,
                    "count": 1,
                    "min": 30,
                    "max": 30
                },
                "2023-01-01": {
                    "avg": 41.92,
                    "count": 1,
                    "min": 41.92,
                    "max": 41.92
                },
                "2023-01-05": {
                    "avg": 61.2,
                    "count": 1,
                    "min": 61.2,
                    "max": 61.2
                }
            },
            "avg": 61.2,
            "avg7": 51.56,
            "avg28": 123.492
        }
    }
}