{
	"data": {
		"normal": {
			"history": {
				"2022-12-09": {
					"avg": 59,
					"count": 1,
					"min": 59,
					"max": 59
				},
				"2022-12-25": {
					"avg": 46,
					"count": 1,
					"min": 46,
					"max": 46
				},
				"2022-12-30": {
					"avg": 98,
					"count": 2,
					"min": 46,
					"max": 150
				},
				"2023-01-04": {
					"avg": 75,
					"count": 1,
					"min": 75,
					"max": 75
				},
				"2023-01-05": {
					"avg": 66,
					"count": 1,
					"min": 66,
					"max": 66
				},
				"2023-01-07": {
					"avg": 150,
					"count": 1,
					"min": 150,
					"max": 150
				},
				"2023-02-12": {
					"avg": 182,
					"count": 1,
					"min": 182,
					"max": 182
				},
				"2023-02-24": {
					"avg": 49,
					"count": 1,
					"min": 49,
					"max": 49
				},
				"2023-03-09": {
					"avg": 43,
					"count": 1,
					"min": 43,
					"max": 43
				},
				"2023-03-13": {
					"avg": 49,
					"count": 1,
					"min": 49,
					"max": 49
				},
				"2023-04-16": {
					"avg": 159,
					"count": 1,
					"min": 159,
					"max": 159
				},
				"2023-04-20": {
					"avg": 66,
					"count": 1,
					"min": 66,
					"max": 66
				},
				"2023-05-17": {
					"avg": 120,
					"count": 1,
					"min": 120,
					"max": 120
				},
				"2023-05-22": {
					"avg": 49,
					"count": 1,
					"min": 49,
					"max": 49
				},
				"2023-05-26": {
					"avg": 139,
					"count": 1,
					"min": 139,
					"max": 139
				},
				"2023-05-30": {
					"avg": 62,
					"count": 1,
					"min": 62,
					"max": 62
				},
				"2023-06-25": {
					"avg": 128,
					"count": 1,
					"min": 128,
					"max": 128
				},
				"2023-07-18": {
					"avg": 40,
					"count": 1,
					"min": 40,
					"max": 40
				},
				"2023-07-21": {
					"avg": 49,
					"count": 1,
					"min": 49,
					"max": 49
				},
				"2023-07-28": {
					"avg": 49,
					"count": 1,
					"min": 49,
					"max": 49
				},
				"2023-09-01": {
					"avg": 148,
					"count": 1,
					"min": 148,
					"max": 148
				},
				"2023-09-07": {
					"avg": 47,
					"count": 1,
					"min": 47,
					"max": 47
				},
				"2023-09-10": {
					"avg": 66,
					"count": 1,
					"min": 66,
					"max": 66
				},
				"2023-10-06": {
					"avg": 216,
					"count": 1,
					"min": 216,
					"max": 216
				},
				"2023-10-25": {
					"avg": 106,
					"count": 2,
					"min": 58,
					"max": 154
				},
				"2023-11-01": {
					"avg": 60,
					"count": 1,
					"min": 60,
					"max": 60
				},
				"2023-11-16": {
					"avg": 59,
					"count": 1,
					"min": 59,
					"max": 59
				},
				"2023-11-25": {
					"avg": 164,
					"count": 1,
					"min": 164,
					"max": 164
				},
				"2024-05-17": {
					"avg": 22,
					"count": 2,
					"min": 22,
					"max": 22
				},
				"2024-05-18": {
					"avg": 35,
					"count": 3,
					"min": 34,
					"max": 38
				},
				"2024-05-19": {
					"avg": 153,
					"count": 1,
					"min": 153,
					"max": 153
				}
			},
			"avg": 35,
			"avg7": 30,
			"avg28": 30
		},
		"reverse": {
			"history": {
				"2023-02-14": {
					"avg": 226,
					"count": 1,
					"min": 226,
					"max": 226
				},
				"2023-02-19": {
					"avg": 145,
					"count": 1,
					"min": 145,
					"max": 145
				},
				"2023-03-15": {
					"avg": 309,
					"count": 2,
					"min": 308,
					"max": 309
				},
				"2023-05-11": {
					"avg": 551,
					"count": 1,
					"min": 551,
					"max": 551
				},
				"2023-09-03": {
					"avg": 101,
					"count": 1,
					"min": 101,
					"max": 101
				},
				"2023-11-01": {
					"avg": 471,
					"count": 1,
					"min": 471,
					"max": 471
				},
				"2023-11-10": {
					"avg": 58,
					"count": 1,
					"min": 58,
					"max": 58
				},
				"2024-05-19": {
					"avg": 98,
					"count": 1,
					"min": 98,
					"max": 98
				}
			},
			"avg": 98,
			"avg7": 98,
			"avg28": 98
		}
	}
}