{
	"data": {
		"normal-good": {
			"history": {
				"2022-12-10": {
					"avg": 750,
					"count": 1,
					"min": 750,
					"max": 750
				},
				"2023-03-06": {
					"avg": 1180,
					"count": 1,
					"min": 1180,
					"max": 1180
				},
				"2024-03-03": {
					"avg": 6500,
					"count": 1,
					"min": 6500,
					"max": 6500
				},
				"2024-03-08": {
					"avg": 751,
					"count": 1,
					"min": 751,
					"max": 751
				},
				"2024-04-05": {
					"avg": 800,
					"count": 1,
					"min": 800,
					"max": 800
				},
				"2024-05-23": {
					"avg": 1400,
					"count": 1,
					"min": 1400,
					"max": 1400
				},
				"2024-10-20": {
					"avg": 1483,
					"count": 2,
					"min": 616,
					"max": 2350
				},
				"2024-11-14": {
					"avg": 1020,
					"count": 1,
					"min": 1020,
					"max": 1020
				},
				"2025-04-23": {
					"avg": 3200,
					"count": 1,
					"min": 3200,
					"max": 3200
				}
			},
			"avg": 1857,
			"avg7": 1180,
			"avg28": 1180
		},
		"normal-nearmint": {
			"history": {
				"2024-10-05": {
					"avg": 1250,
					"count": 1,
					"min": 1250,
					"max": 1250
				}
			},
			"avg": 1250,
			"avg7": -1,
			"avg28": -1
		}
	}
}