{
	"data": {
		"normal-good": {
			"history": {
				"2024-11-18": {
					"avg": 149,
					"count": 1,
					"min": 149,
					"max": 149
				},
				"2024-11-20": {
					"avg": 190,
					"count": 1,
					"min": 190,
					"max": 190
				},
				"2024-11-24": {
					"avg": 149,
					"count": 1,
					"min": 149,
					"max": 149
				},
				"2024-12-04": {
					"avg": 1580,
					"count": 1,
					"min": 1580,
					"max": 1580
				},
				"2024-12-09": {
					"avg": 149,
					"count": 1,
					"min": 149,
					"max": 149
				},
				"2024-12-29": {
					"avg": 1606,
					"count": 1,
					"min": 1606,
					"max": 1606
				}
			},
			"avg": 637,
			"avg7": -1,
			"avg28": -1
		},
		"normal-nearmint": {
			"history": {
				"2024-11-16": {
					"avg": 1847,
					"count": 1,
					"min": 1847,
					"max": 1847
				},
				"2024-11-20": {
					"avg": 1601,
					"count": 1,
					"min": 1601,
					"max": 1601
				},
				"2024-12-23": {
					"avg": 1855,
					"count": 1,
					"min": 1855,
					"max": 1855
				},
				"2024-12-26": {
					"avg": 2562,
					"count": 1,
					"min": 2562,
					"max": 2562
				},
				"2024-12-29": {
					"avg": 1863,
					"count": 1,
					"min": 1863,
					"max": 1863
				}
			},
			"avg": 1946,
			"avg7": -1,
			"avg28": -1
		}
	}
}