{
    "data": {
        "holo": {
            "history": {
                "2022-12-07": {
                    "avg": 18.49,
                    "count": 1,
                    "min": 18.49,
                    "max": 18.49
                },
                "2022-12-09": {
                    "avg": 8.18,
                    "count": 2,
                    "min": 8.18,
                    "max": 8.18
                },
                "2022-12-11": {
                    "avg": 12.045,
                    "count": 2,
                    "min": 8.1,
                    "max": 15.99
                },
                "2022-12-14": {
                    "avg": 12.88,
                    "count": 1,
                    "min": 12.88,
                    "max": 12.88
                },
                "2022-12-16": {
                    "avg": 14.495000000000001,
                    "count": 2,
                    "min": 8.22,
                    "max": 20.77
                },
                "2022-12-20": {
                    "avg": 8.99,
                    "count": 1,
                    "min": 8.99,
                    "max": 8.99
                },
                "2022-12-21": {
                    "avg": 14.985,
                    "count": 2,
                    "min": 8.98,
                    "max": 20.99
                },
                "2022-12-22": {
                    "avg": 8,
                    "count": 1,
                    "min": 8,
                    "max": 8
                },
                "2022-12-23": {
                    "avg": 8.22,
                    "count": 2,
                    "min": 8.22,
                    "max": 8.22
                },
                "2022-12-24": {
                    "avg": 7.25,
                    "count": 1,
                    "min": 7.25,
                    "max": 7.25
                },
                "2022-12-26": {
                    "avg": 7.25,
                    "count": 1,
                    "min": 7.25,
                    "max": 7.25
                },
                "2022-12-30": {
                    "avg": 8.26,
                    "count": 1,
                    "min": 8.26,
                    "max": 8.26
                },
                "2023-01-03": {
                    "avg": 7,
                    "count": 1,
                    "min": 7,
                    "max": 7
                },
                "2023-01-04": {
                    "avg": 7,
                    "count": 1,
                    "min": 7,
                    "max": 7
                },
                "2023-01-08": {
                    "avg": 7.09,
                    "count": 1,
                    "min": 7.09,
                    "max": 7.09
                },
                "2023-01-11": {
                    "avg": 8.7,
                    "count": 2,
                    "min": 8.19,
                    "max": 9.21
                },
                "2023-02-06": {
                    "avg": 18.27,
                    "count": 1,
                    "min": 18.27,
                    "max": 18.27
                },
                "2023-02-08": {
                    "avg": 15.99,
                    "count": 1,
                    "min": 15.99,
                    "max": 15.99
                },
                "2023-02-12": {
                    "avg": 5.245,
                    "count": 2,
                    "min": 5,
                    "max": 5.49
                },
                "2023-02-16": {
                    "avg": 18.98,
                    "count": 1,
                    "min": 18.98,
                    "max": 18.98
                },
                "2023-02-17": {
                    "avg": 8.504999999999999,
                    "count": 2,
                    "min": 7.52,
                    "max": 9.49
                },
                "2023-02-18": {
                    "avg": 7.52,
                    "count": 1,
                    "min": 7.52,
                    "max": 7.52
                },
                "2023-03-07": {
                    "avg": 8.9,
                    "count": 1,
                    "min": 8.9,
                    "max": 8.9
                },
                "2023-03-14": {
                    "avg": 16.94,
                    "count": 2,
                    "min": 8.9,
                    "max": 24.98
                },
                "2023-03-16": {
                    "avg": 13.129999999999999,
                    "count": 2,
                    "min": 8.9,
                    "max": 17.36
                },
                "2023-03-17": {
                    "avg": 8.9,
                    "count": 2,
                    "min": 8.9,
                    "max": 8.9
                },
                "2023-03-18": {
                    "avg": 8.9,
                    "count": 1,
                    "min": 8.9,
                    "max": 8.9
                },
                "2023-03-24": {
                    "avg": 18.72,
                    "count": 1,
                    "min": 18.72,
                    "max": 18.72
                },
                "2023-03-25": {
                    "avg": 14.155,
                    "count": 2,
                    "min": 9.59,
                    "max": 18.72
                },
                "2023-04-04": {
                    "avg": 20.25,
                    "count": 1,
                    "min": 20.25,
                    "max": 20.25
                },
                "2023-04-10": {
                    "avg": 39.99,
                    "count": 1,
                    "min": 39.99,
                    "max": 39.99
                },
                "2023-04-13": {
                    "avg": 8.81,
                    "count": 2,
                    "min": 8.64,
                    "max": 8.98
                },
                "2023-04-15": {
                    "avg": 8.54,
                    "count": 2,
                    "min": 8.44,
                    "max": 8.64
                },
                "2023-04-16": {
                    "avg": 8.64,
                    "count": 1,
                    "min": 8.64,
                    "max": 8.64
                },
                "2023-04-20": {
                    "avg": 24.99,
                    "count": 1,
                    "min": 24.99,
                    "max": 24.99
                },
                "2023-04-21": {
                    "avg": 14.5,
                    "count": 2,
                    "min": 5,
                    "max": 24
                },
                "2023-04-23": {
                    "avg": 24,
                    "count": 1,
                    "min": 24,
                    "max": 24
                },
                "2023-04-25": {
                    "avg": 9.48,
                    "count": 1,
                    "min": 9.48,
                    "max": 9.48
                },
                "2023-04-26": {
                    "avg": 8.68,
                    "count": 2,
                    "min": 8.63,
                    "max": 8.73
                },
                "2023-04-30": {
                    "avg": 9,
                    "count": 1,
                    "min": 9,
                    "max": 9
                },
                "2023-05-03": {
                    "avg": 8.58,
                    "count": 1,
                    "min": 8.58,
                    "max": 8.58
                },
                "2023-05-05": {
                    "avg": 7.09,
                    "count": 2,
                    "min": 4.99,
                    "max": 9.19
                },
                "2023-05-11": {
                    "avg": 9.791428571428572,
                    "count": 7,
                    "min": 6.99,
                    "max": 16.98
                },
                "2023-05-12": {
                    "avg": 10.76,
                    "count": 1,
                    "min": 10.76,
                    "max": 10.76
                },
                "2023-05-16": {
                    "avg": 6.49,
                    "count": 1,
                    "min": 6.49,
                    "max": 6.49
                },
                "2023-05-18": {
                    "avg": 7.99,
                    "count": 1,
                    "min": 7.99,
                    "max": 7.99
                },
                "2023-05-27": {
                    "avg": 10.49,
                    "count": 1,
                    "min": 10.49,
                    "max": 10.49
                },
                "2023-05-29": {
                    "avg": 11.99,
                    "count": 1,
                    "min": 11.99,
                    "max": 11.99
                },
                "2023-05-30": {
                    "avg": 7.99,
                    "count": 1,
                    "min": 7.99,
                    "max": 7.99
                },
                "2023-05-31": {
                    "avg": 6.16,
                    "count": 1,
                    "min": 6.16,
                    "max": 6.16
                },
                "2023-06-10": {
                    "avg": 16.98,
                    "count": 1,
                    "min": 16.98,
                    "max": 16.98
                },
                "2023-06-30": {
                    "avg": 9.765,
                    "count": 2,
                    "min": 8.48,
                    "max": 11.05
                },
                "2023-07-01": {
                    "avg": 21.02,
                    "count": 1,
                    "min": 21.02,
                    "max": 21.02
                },
                "2023-07-03": {
                    "avg": 7.99,
                    "count": 1,
                    "min": 7.99,
                    "max": 7.99
                },
                "2023-07-08": {
                    "avg": 7.09,
                    "count": 1,
                    "min": 7.09,
                    "max": 7.09
                },
                "2023-07-15": {
                    "avg": 21.84,
                    "count": 1,
                    "min": 21.84,
                    "max": 21.84
                },
                "2023-07-21": {
                    "avg": 10.5,
                    "count": 1,
                    "min": 10.5,
                    "max": 10.5
                }
            },
            "avg": 10.5,
            "avg7": 16.17,
            "avg28": 12.567142857142859
        }
    }
}