{
	"data": {
		"normal-good": {
			"history": {
				"2022-12-03": {
					"avg": 220,
					"count": 1,
					"min": 220,
					"max": 220
				},
				"2022-12-16": {
					"avg": 300,
					"count": 1,
					"min": 300,
					"max": 300
				},
				"2022-12-20": {
					"avg": 266,
					"count": 1,
					"min": 266,
					"max": 266
				},
				"2022-12-25": {
					"avg": 266,
					"count": 1,
					"min": 266,
					"max": 266
				},
				"2023-01-02": {
					"avg": 266,
					"count": 1,
					"min": 266,
					"max": 266
				},
				"2024-06-30": {
					"avg": 285,
					"count": 1,
					"min": 285,
					"max": 285
				},
				"2024-08-29": {
					"avg": 279,
					"count": 1,
					"min": 279,
					"max": 279
				},
				"2024-09-12": {
					"avg": 220,
					"count": 1,
					"min": 220,
					"max": 220
				},
				"2024-09-16": {
					"avg": 290,
					"count": 1,
					"min": 290,
					"max": 290
				},
				"2024-10-14": {
					"avg": 450,
					"count": 1,
					"min": 450,
					"max": 450
				},
				"2024-11-06": {
					"avg": 300,
					"count": 1,
					"min": 300,
					"max": 300
				},
				"2024-11-25": {
					"avg": 450,
					"count": 1,
					"min": 450,
					"max": 450
				},
				"2024-12-08": {
					"avg": 395,
					"count": 1,
					"min": 395,
					"max": 395
				},
				"2024-12-19": {
					"avg": 379,
					"count": 1,
					"min": 379,
					"max": 379
				}
			},
			"avg": 312,
			"avg7": 266,
			"avg28": 275
		},
		"normal-nearmint": {
			"history": {
				"2024-08-10": {
					"avg": 180,
					"count": 1,
					"min": 180,
					"max": 180
				}
			},
			"avg": 180,
			"avg7": -1,
			"avg28": -1
		}
	}
}