{
    "data": {
        "normal": {
            "history": {
                "2022-12-07": {
                    "avg": 0.03,
                    "count": 1,
                    "min": 0.03,
                    "max": 0.03
                },
                "2022-12-10": {
                    "avg": 0.05,
                    "count": 1,
                    "min": 0.05,
                    "max": 0.05
                },
                "2022-12-16": {
                    "avg": 0.03,
                    "count": 2,
                    "min": 0.03,
                    "max": 0.03
                },
                "2022-12-18": {
                    "avg": 0.02,
                    "count": 3,
                    "min": 0.02,
                    "max": 0.02
                },
                "2022-12-20": {
                    "avg": 1.01,
                    "count": 3,
                    "min": 1.01,
                    "max": 1.01
                },
                "2022-12-24": {
                    "avg": 1,
                    "count": 1,
                    "min": 1,
                    "max": 1
                },
                "2022-12-27": {
                    "avg": 0.04,
                    "count": 1,
                    "min": 0.04,
                    "max": 0.04
                },
                "2022-12-28": {
                    "avg": 0.04,
                    "count": 4,
                    "min": 0.04,
                    "max": 0.04
                },
                "2022-12-29": {
                    "avg": 0.04,
                    "count": 1,
                    "min": 0.04,
                    "max": 0.04
                },
                "2023-01-03": {
                    "avg": 4.07,
                    "count": 1,
                    "min": 4.07,
                    "max": 4.07
                },
                "2023-01-04": {
                    "avg": 0.01,
                    "count": 1,
                    "min": 0.01,
                    "max": 0.01
                },
                "2023-01-06": {
                    "avg": 0.8,
                    "count": 1,
                    "min": 0.8,
                    "max": 0.8
                },
                "2023-01-08": {
                    "avg": 0.03,
                    "count": 1,
                    "min": 0.03,
                    "max": 0.03
                },
                "2023-01-12": {
                    "avg": 0.55,
                    "count": 2,
                    "min": 0.09,
                    "max": 1.01
                },
                "2023-02-12": {
                    "avg": 2.03,
                    "count": 1,
                    "min": 2.03,
                    "max": 2.03
                },
                "2023-03-02": {
                    "avg": 0.02,
                    "count": 1,
                    "min": 0.02,
                    "max": 0.02
                },
                "2023-03-07": {
                    "avg": 0.03,
                    "count": 1,
                    "min": 0.03,
                    "max": 0.03
                },
                "2023-03-16": {
                    "avg": 1.01,
                    "count": 1,
                    "min": 1.01,
                    "max": 1.01
                },
                "2023-03-18": {
                    "avg": 0.03,
                    "count": 1,
                    "min": 0.03,
                    "max": 0.03
                },
                "2023-03-24": {
                    "avg": 2.02,
                    "count": 1,
                    "min": 2.02,
                    "max": 2.02
                },
                "2023-03-25": {
                    "avg": 0.03,
                    "count": 1,
                    "min": 0.03,
                    "max": 0.03
                },
                "2023-03-27": {
                    "avg": 0.03,
                    "count": 3,
                    "min": 0.03,
                    "max": 0.03
                },
                "2023-04-02": {
                    "avg": 0.03,
                    "count": 1,
                    "min": 0.03,
                    "max": 0.03
                },
                "2023-04-05": {
                    "avg": 0.065,
                    "count": 2,
                    "min": 0.03,
                    "max": 0.1
                },
                "2023-04-10": {
                    "avg": 0.03,
                    "count": 1,
                    "min": 0.03,
                    "max": 0.03
                },
                "2023-04-11": {
                    "avg": 1,
                    "count": 3,
                    "min": 1,
                    "max": 1
                },
                "2023-04-12": {
                    "avg": 0.03,
                    "count": 1,
                    "min": 0.03,
                    "max": 0.03
                },
                "2023-04-15": {
                    "avg": 3.74,
                    "count": 1,
                    "min": 3.74,
                    "max": 3.74
                },
                "2023-04-16": {
                    "avg": 0.04,
                    "count": 2,
                    "min": 0.03,
                    "max": 0.05
                },
                "2023-04-21": {
                    "avg": 0.03,
                    "count": 2,
                    "min": 0.03,
                    "max": 0.03
                },
                "2023-04-23": {
                    "avg": 0.05,
                    "count": 1,
                    "min": 0.05,
                    "max": 0.05
                },
                "2023-04-26": {
                    "avg": 0.03,
                    "count": 1,
                    "min": 0.03,
                    "max": 0.03
                },
                "2023-04-29": {
                    "avg": 0.03,
                    "count": 1,
                    "min": 0.03,
                    "max": 0.03
                },
                "2023-04-30": {
                    "avg": 1.0299999999999998,
                    "count": 2,
                    "min": 0.03,
                    "max": 2.03
                },
                "2023-05-03": {
                    "avg": 0.04,
                    "count": 1,
                    "min": 0.04,
                    "max": 0.04
                },
                "2023-05-06": {
                    "avg": 0.03,
                    "count": 1,
                    "min": 0.03,
                    "max": 0.03
                },
                "2023-05-07": {
                    "avg": 0.07,
                    "count": 4,
                    "min": 0.03,
                    "max": 0.1
                },
                "2023-05-09": {
                    "avg": 1.02,
                    "count": 1,
                    "min": 1.02,
                    "max": 1.02
                },
                "2023-05-10": {
                    "avg": 0.04,
                    "count": 1,
                    "min": 0.04,
                    "max": 0.04
                },
                "2023-05-11": {
                    "avg": 0.05,
                    "count": 1,
                    "min": 0.05,
                    "max": 0.05
                },
                "2023-05-13": {
                    "avg": 0.03,
                    "count": 1,
                    "min": 0.03,
                    "max": 0.03
                },
                "2023-05-23": {
                    "avg": 0.065,
                    "count": 2,
                    "min": 0.03,
                    "max": 0.1
                },
                "2023-05-25": {
                    "avg": 0.055,
                    "count": 2,
                    "min": 0.03,
                    "max": 0.08
                },
                "2023-05-26": {
                    "avg": 0.03,
                    "count": 1,
                    "min": 0.03,
                    "max": 0.03
                }
            },
            "avg": 0.03,
            "avg7": 0.054000000000000006,
            "avg28": 0.22470588235294117
        },
        "reverse": {
            "history": {
                "2022-12-09": {
                    "avg": 0.1,
                    "count": 1,
                    "min": 0.1,
                    "max": 0.1
                },
                "2022-12-10": {
                    "avg": 0.1,
                    "count": 1,
                    "min": 0.1,
                    "max": 0.1
                },
                "2022-12-12": {
                    "avg": 4.25,
                    "count": 1,
                    "min": 4.25,
                    "max": 4.25
                },
                "2022-12-14": {
                    "avg": 0.12,
                    "count": 1,
                    "min": 0.12,
                    "max": 0.12
                },
                "2022-12-16": {
                    "avg": 0.12,
                    "count": 1,
                    "min": 0.12,
                    "max": 0.12
                },
                "2022-12-27": {
                    "avg": 0.13,
                    "count": 1,
                    "min": 0.13,
                    "max": 0.13
                },
                "2022-12-30": {
                    "avg": 0.13,
                    "count": 1,
                    "min": 0.13,
                    "max": 0.13
                },
                "2023-01-03": {
                    "avg": 0.13,
                    "count": 1,
                    "min": 0.13,
                    "max": 0.13
                },
                "2023-01-04": {
                    "avg": 0.5033333333333334,
                    "count": 3,
                    "min": 0.2,
                    "max": 1.11
                },
                "2023-01-08": {
                    "avg": 0.13,
                    "count": 3,
                    "min": 0.13,
                    "max": 0.13
                },
                "2023-02-06": {
                    "avg": 0.13,
                    "count": 1,
                    "min": 0.13,
                    "max": 0.13
                },
                "2023-02-18": {
                    "avg": 2.13,
                    "count": 1,
                    "min": 2.13,
                    "max": 2.13
                },
                "2023-03-03": {
                    "avg": 0.18,
                    "count": 1,
                    "min": 0.18,
                    "max": 0.18
                },
                "2023-03-14": {
                    "avg": 0.24,
                    "count": 1,
                    "min": 0.24,
                    "max": 0.24
                },
                "2023-03-15": {
                    "avg": 0.155,
                    "count": 2,
                    "min": 0.15,
                    "max": 0.16
                },
                "2023-03-16": {
                    "avg": 1.14,
                    "count": 1,
                    "min": 1.14,
                    "max": 1.14
                },
                "2023-03-19": {
                    "avg": 0.16,
                    "count": 1,
                    "min": 0.16,
                    "max": 0.16
                },
                "2023-03-26": {
                    "avg": 0.25,
                    "count": 1,
                    "min": 0.25,
                    "max": 0.25
                },
                "2023-04-03": {
                    "avg": 0.175,
                    "count": 2,
                    "min": 0.15,
                    "max": 0.2
                },
                "2023-04-05": {
                    "avg": 0.1,
                    "count": 1,
                    "min": 0.1,
                    "max": 0.1
                },
                "2023-04-09": {
                    "avg": 0.19,
                    "count": 1,
                    "min": 0.19,
                    "max": 0.19
                },
                "2023-04-18": {
                    "avg": 0.2,
                    "count": 1,
                    "min": 0.2,
                    "max": 0.2
                },
                "2023-04-22": {
                    "avg": 0.2,
                    "count": 1,
                    "min": 0.2,
                    "max": 0.2
                },
                "2023-04-29": {
                    "avg": 0.18,
                    "count": 1,
                    "min": 0.18,
                    "max": 0.18
                },
                "2023-05-01": {
                    "avg": 0.1,
                    "count": 1,
                    "min": 0.1,
                    "max": 0.1
                },
                "2023-05-03": {
                    "avg": 0.175,
                    "count": 2,
                    "min": 0.12,
                    "max": 0.23
                },
                "2023-05-06": {
                    "avg": 0.16999999999999998,
                    "count": 2,
                    "min": 0.1,
                    "max": 0.24
                },
                "2023-05-08": {
                    "avg": 0.6799999999999999,
                    "count": 2,
                    "min": 0.23,
                    "max": 1.13
                },
                "2023-05-09": {
                    "avg": 0.17,
                    "count": 1,
                    "min": 0.17,
                    "max": 0.17
                },
                "2023-05-22": {
                    "avg": 0.19,
                    "count": 1,
                    "min": 0.19,
                    "max": 0.19
                },
                "2023-05-25": {
                    "avg": 0.23,
                    "count": 1,
                    "min": 0.23,
                    "max": 0.23
                }
            },
            "avg": 0.23,
            "avg7": 0.21000000000000002,
            "avg28": 0.2654545454545455
        }
    }
}