{
    "data": {
        "holo": {
            "history": {
                "2022-11-12": {
                    "avg": 0.6033333333333334,
                    "count": 3
                },
                "2022-12-06": {
                    "avg": 1.46,
                    "count": 1,
                    "min": 1.46,
                    "max": 1.46
                },
                "2022-12-07": {
                    "avg": 2.794,
                    "count": 5,
                    "min": 1,
                    "max": 3.99
                }
            },
            "avg": 2.794,
            "avg7": 2.5716666666666668,
            "avg28": 1.9155555555555555
        }
    }
}