{
	"data": {
		"holo-good": {
			"history": {
				"2022-12-07": {
					"avg": 13185,
					"count": 1,
					"min": 13185,
					"max": 13185
				},
				"2022-12-16": {
					"avg": 10048,
					"count": 1,
					"min": 10048,
					"max": 10048
				},
				"2022-12-23": {
					"avg": 11974,
					"count": 1,
					"min": 11974,
					"max": 11974
				},
				"2023-01-03": {
					"avg": 12000,
					"count": 1,
					"min": 12000,
					"max": 12000
				},
				"2023-02-11": {
					"avg": 18599,
					"count": 1,
					"min": 18599,
					"max": 18599
				},
				"2023-02-16": {
					"avg": 18598,
					"count": 1,
					"min": 18598,
					"max": 18598
				},
				"2023-02-17": {
					"avg": 18597,
					"count": 1,
					"min": 18597,
					"max": 18597
				},
				"2023-02-22": {
					"avg": 15594,
					"count": 1,
					"min": 15594,
					"max": 15594
				},
				"2023-03-03": {
					"avg": 10025,
					"count": 2,
					"min": 8650,
					"max": 11399
				},
				"2023-03-19": {
					"avg": 18495,
					"count": 1,
					"min": 18495,
					"max": 18495
				},
				"2023-03-28": {
					"avg": 10100,
					"count": 1,
					"min": 10100,
					"max": 10100
				},
				"2023-04-06": {
					"avg": 19993,
					"count": 1,
					"min": 19993,
					"max": 19993
				},
				"2023-04-12": {
					"avg": 19899,
					"count": 1,
					"min": 19899,
					"max": 19899
				},
				"2023-04-16": {
					"avg": 13706,
					"count": 1,
					"min": 13706,
					"max": 13706
				},
				"2023-04-18": {
					"avg": 15248,
					"count": 2,
					"min": 11499,
					"max": 18998
				},
				"2023-04-22": {
					"avg": 17000,
					"count": 1,
					"min": 17000,
					"max": 17000
				},
				"2023-04-26": {
					"avg": 16899,
					"count": 1,
					"min": 16899,
					"max": 16899
				},
				"2023-04-29": {
					"avg": 17047,
					"count": 2,
					"min": 15099,
					"max": 18995
				},
				"2023-05-02": {
					"avg": 18045,
					"count": 1,
					"min": 18045,
					"max": 18045
				},
				"2023-05-10": {
					"avg": 20500,
					"count": 1,
					"min": 20500,
					"max": 20500
				},
				"2023-05-13": {
					"avg": 21712,
					"count": 3,
					"min": 9440,
					"max": 27999
				},
				"2023-05-16": {
					"avg": 20000,
					"count": 1,
					"min": 20000,
					"max": 20000
				},
				"2023-05-23": {
					"avg": 17300,
					"count": 3,
					"min": 17300,
					"max": 17300
				},
				"2023-05-26": {
					"avg": 17498,
					"count": 1,
					"min": 17498,
					"max": 17498
				},
				"2023-05-30": {
					"avg": 25999,
					"count": 1,
					"min": 25999,
					"max": 25999
				},
				"2023-06-26": {
					"avg": 23995,
					"count": 1,
					"min": 23995,
					"max": 23995
				},
				"2023-06-30": {
					"avg": 24945,
					"count": 1,
					"min": 24945,
					"max": 24945
				},
				"2023-07-03": {
					"avg": 24945,
					"count": 1,
					"min": 24945,
					"max": 24945
				},
				"2023-07-31": {
					"avg": 33039,
					"count": 1,
					"min": 33039,
					"max": 33039
				},
				"2023-08-24": {
					"avg": 20000,
					"count": 1,
					"min": 20000,
					"max": 20000
				},
				"2023-09-16": {
					"avg": 21045,
					"count": 1,
					"min": 21045,
					"max": 21045
				},
				"2023-09-23": {
					"avg": 19368,
					"count": 1,
					"min": 19368,
					"max": 19368
				},
				"2023-09-25": {
					"avg": 20875,
					"count": 1,
					"min": 20875,
					"max": 20875
				},
				"2023-09-26": {
					"avg": 21860,
					"count": 1,
					"min": 21860,
					"max": 21860
				},
				"2023-10-02": {
					"avg": 20994,
					"count": 1,
					"min": 20994,
					"max": 20994
				},
				"2023-10-13": {
					"avg": 18500,
					"count": 1,
					"min": 18500,
					"max": 18500
				},
				"2023-10-26": {
					"avg": 12999,
					"count": 1,
					"min": 12999,
					"max": 12999
				},
				"2023-11-03": {
					"avg": 20946,
					"count": 1,
					"min": 20946,
					"max": 20946
				},
				"2023-11-05": {
					"avg": 19369,
					"count": 1,
					"min": 19369,
					"max": 19369
				},
				"2023-11-24": {
					"avg": 18531,
					"count": 3,
					"min": 17598,
					"max": 19000
				},
				"2023-11-26": {
					"avg": 17598,
					"count": 1,
					"min": 17598,
					"max": 17598
				},
				"2023-11-27": {
					"avg": 16299,
					"count": 1,
					"min": 16299,
					"max": 16299
				},
				"2024-05-17": {
					"avg": 16817,
					"count": 4,
					"min": 13124,
					"max": 21499
				},
				"2024-05-18": {
					"avg": 18308,
					"count": 2,
					"min": 16122,
					"max": 20495
				},
				"2024-05-19": {
					"avg": 19687,
					"count": 1,
					"min": 19687,
					"max": 19687
				},
				"2024-06-12": {
					"avg": 20000,
					"count": 1,
					"min": 20000,
					"max": 20000
				},
				"2024-06-15": {
					"avg": 17510,
					"count": 1,
					"min": 17510,
					"max": 17510
				},
				"2024-06-30": {
					"avg": 16972,
					"count": 1,
					"min": 16972,
					"max": 16972
				},
				"2024-07-19": {
					"avg": 19121,
					"count": 1,
					"min": 19121,
					"max": 19121
				},
				"2024-08-24": {
					"avg": 22500,
					"count": 1,
					"min": 22500,
					"max": 22500
				}
			},
			"avg": 18261,
			"avg7": 17653,
			"avg28": 17653
		},
		"holo-nearmint": {
			"history": {
				"2024-05-26": {
					"avg": 25493,
					"count": 1,
					"min": 25493,
					"max": 25493
				},
				"2024-05-31": {
					"avg": 23746,
					"count": 2,
					"min": 21999,
					"max": 25493
				},
				"2024-06-07": {
					"avg": 22200,
					"count": 1,
					"min": 22200,
					"max": 22200
				},
				"2024-06-11": {
					"avg": 27985,
					"count": 1,
					"min": 27985,
					"max": 27985
				},
				"2024-06-12": {
					"avg": 11999,
					"count": 1,
					"min": 11999,
					"max": 11999
				},
				"2024-06-14": {
					"avg": 25098,
					"count": 1,
					"min": 25098,
					"max": 25098
				},
				"2024-06-16": {
					"avg": 32998,
					"count": 1,
					"min": 32998,
					"max": 32998
				},
				"2024-06-25": {
					"avg": 18534,
					"count": 1,
					"min": 18534,
					"max": 18534
				},
				"2024-06-26": {
					"avg": 31969,
					"count": 1,
					"min": 31969,
					"max": 31969
				},
				"2024-07-06": {
					"avg": 12000,
					"count": 1,
					"min": 12000,
					"max": 12000
				},
				"2024-07-07": {
					"avg": 21108,
					"count": 2,
					"min": 20117,
					"max": 22099
				},
				"2024-07-19": {
					"avg": 24599,
					"count": 1,
					"min": 24599,
					"max": 24599
				},
				"2024-07-23": {
					"avg": 20019,
					"count": 1,
					"min": 20019,
					"max": 20019
				},
				"2024-07-25": {
					"avg": 23799,
					"count": 1,
					"min": 23799,
					"max": 23799
				},
				"2024-08-05": {
					"avg": 20998,
					"count": 1,
					"min": 20998,
					"max": 20998
				},
				"2024-08-14": {
					"avg": 20598,
					"count": 1,
					"min": 20598,
					"max": 20598
				},
				"2024-08-15": {
					"avg": 24900,
					"count": 1,
					"min": 24900,
					"max": 24900
				},
				"2024-08-31": {
					"avg": 26195,
					"count": 1,
					"min": 26195,
					"max": 26195
				},
				"2024-09-02": {
					"avg": 24999,
					"count": 1,
					"min": 24999,
					"max": 24999
				},
				"2024-09-12": {
					"avg": 26195,
					"count": 1,
					"min": 26195,
					"max": 26195
				},
				"2024-09-14": {
					"avg": 24998,
					"count": 1,
					"min": 24998,
					"max": 24998
				},
				"2024-09-21": {
					"avg": 12000,
					"count": 1,
					"min": 12000,
					"max": 12000
				}
			},
			"avg": 22804,
			"avg7": -1,
			"avg28": -1
		},
		"holo-played": {
			"history": {
				"2024-07-04": {
					"avg": 14028,
					"count": 1,
					"min": 14028,
					"max": 14028
				},
				"2024-08-08": {
					"avg": 15526,
					"count": 1,
					"min": 15526,
					"max": 15526
				},
				"2024-09-20": {
					"avg": 10498,
					"count": 1,
					"min": 10498,
					"max": 10498
				}
			},
			"avg": 13351,
			"avg7": -1,
			"avg28": -1
		},
		"holo-used": {
			"history": {
				"2024-07-26": {
					"avg": 17058,
					"count": 1,
					"min": 17058,
					"max": 17058
				}
			},
			"avg": 17058,
			"avg7": -1,
			"avg28": -1
		},
		"holo-poor": {
			"history": {
				"2024-05-29": {
					"avg": 10098,
					"count": 1,
					"min": 10098,
					"max": 10098
				},
				"2024-06-07": {
					"avg": 9899,
					"count": 1,
					"min": 9899,
					"max": 9899
				},
				"2024-06-25": {
					"avg": 9898,
					"count": 1,
					"min": 9898,
					"max": 9898
				}
			},
			"avg": 9965,
			"avg7": -1,
			"avg28": -1
		}
	}
}