{
	"data": {
		"holo-good": {
			"history": {
				"2022-12-07": {
					"avg": 572,
					"count": 1,
					"min": 572,
					"max": 572
				},
				"2022-12-10": {
					"avg": 1147,
					"count": 2,
					"min": 1147,
					"max": 1147
				},
				"2022-12-15": {
					"avg": 380,
					"count": 1,
					"min": 380,
					"max": 380
				},
				"2023-01-01": {
					"avg": 518,
					"count": 1,
					"min": 518,
					"max": 518
				},
				"2023-01-08": {
					"avg": 484,
					"count": 1,
					"min": 484,
					"max": 484
				},
				"2023-02-06": {
					"avg": 546,
					"count": 1,
					"min": 546,
					"max": 546
				},
				"2023-02-11": {
					"avg": 548,
					"count": 1,
					"min": 548,
					"max": 548
				},
				"2023-02-16": {
					"avg": 499,
					"count": 1,
					"min": 499,
					"max": 499
				},
				"2023-03-07": {
					"avg": 547,
					"count": 1,
					"min": 547,
					"max": 547
				},
				"2023-03-14": {
					"avg": 425,
					"count": 1,
					"min": 425,
					"max": 425
				},
				"2023-03-16": {
					"avg": 568,
					"count": 1,
					"min": 568,
					"max": 568
				},
				"2023-03-19": {
					"avg": 548,
					"count": 1,
					"min": 548,
					"max": 548
				},
				"2023-03-23": {
					"avg": 634,
					"count": 1,
					"min": 634,
					"max": 634
				},
				"2023-03-25": {
					"avg": 624,
					"count": 1,
					"min": 624,
					"max": 624
				},
				"2023-03-29": {
					"avg": 548,
					"count": 1,
					"min": 548,
					"max": 548
				},
				"2023-04-05": {
					"avg": 570,
					"count": 1,
					"min": 570,
					"max": 570
				},
				"2023-04-06": {
					"avg": 449,
					"count": 2,
					"min": 449,
					"max": 449
				},
				"2023-04-10": {
					"avg": 544,
					"count": 1,
					"min": 544,
					"max": 544
				},
				"2023-04-11": {
					"avg": 948,
					"count": 1,
					"min": 948,
					"max": 948
				},
				"2023-04-12": {
					"avg": 599,
					"count": 1,
					"min": 599,
					"max": 599
				},
				"2023-04-13": {
					"avg": 595,
					"count": 1,
					"min": 595,
					"max": 595
				},
				"2023-04-15": {
					"avg": 499,
					"count": 1,
					"min": 499,
					"max": 499
				},
				"2023-04-20": {
					"avg": 579,
					"count": 3,
					"min": 539,
					"max": 599
				},
				"2023-04-21": {
					"avg": 595,
					"count": 1,
					"min": 595,
					"max": 595
				},
				"2023-04-29": {
					"avg": 540,
					"count": 1,
					"min": 540,
					"max": 540
				},
				"2023-05-03": {
					"avg": 595,
					"count": 1,
					"min": 595,
					"max": 595
				},
				"2023-05-04": {
					"avg": 99,
					"count": 1,
					"min": 99,
					"max": 99
				},
				"2023-05-05": {
					"avg": 599,
					"count": 1,
					"min": 599,
					"max": 599
				},
				"2023-05-18": {
					"avg": 559,
					"count": 2,
					"min": 520,
					"max": 598
				},
				"2023-06-12": {
					"avg": 633,
					"count": 1,
					"min": 633,
					"max": 633
				},
				"2023-06-16": {
					"avg": 499,
					"count": 2,
					"min": 499,
					"max": 499
				},
				"2023-07-15": {
					"avg": 539,
					"count": 1,
					"min": 539,
					"max": 539
				},
				"2023-07-31": {
					"avg": 499,
					"count": 2,
					"min": 499,
					"max": 499
				},
				"2023-08-04": {
					"avg": 570,
					"count": 3,
					"min": 499,
					"max": 613
				},
				"2023-08-08": {
					"avg": 496,
					"count": 3,
					"min": 399,
					"max": 589
				},
				"2023-08-12": {
					"avg": 829,
					"count": 1,
					"min": 829,
					"max": 829
				},
				"2023-08-19": {
					"avg": 491,
					"count": 1,
					"min": 491,
					"max": 491
				},
				"2023-10-01": {
					"avg": 598,
					"count": 1,
					"min": 598,
					"max": 598
				},
				"2023-10-05": {
					"avg": 278,
					"count": 1,
					"min": 278,
					"max": 278
				},
				"2023-10-09": {
					"avg": 379,
					"count": 2,
					"min": 378,
					"max": 379
				},
				"2023-10-14": {
					"avg": 499,
					"count": 4,
					"min": 427,
					"max": 598
				},
				"2023-10-17": {
					"avg": 565,
					"count": 3,
					"min": 499,
					"max": 598
				},
				"2023-10-20": {
					"avg": 425,
					"count": 1,
					"min": 425,
					"max": 425
				},
				"2023-11-07": {
					"avg": 439,
					"count": 1,
					"min": 439,
					"max": 439
				},
				"2023-11-09": {
					"avg": 494,
					"count": 4,
					"min": 439,
					"max": 598
				},
				"2023-11-24": {
					"avg": 564,
					"count": 2,
					"min": 539,
					"max": 589
				},
				"2023-11-26": {
					"avg": 626,
					"count": 11,
					"min": 505,
					"max": 705
				},
				"2024-05-17": {
					"avg": 999,
					"count": 1,
					"min": 999,
					"max": 999
				},
				"2024-05-18": {
					"avg": 666,
					"count": 1,
					"min": 666,
					"max": 666
				},
				"2024-05-21": {
					"avg": 927,
					"count": 1,
					"min": 927,
					"max": 927
				},
				"2024-05-24": {
					"avg": 998,
					"count": 1,
					"min": 998,
					"max": 998
				},
				"2024-05-30": {
					"avg": 1099,
					"count": 4,
					"min": 1099,
					"max": 1099
				},
				"2024-07-18": {
					"avg": 823,
					"count": 1,
					"min": 823,
					"max": 823
				},
				"2024-07-31": {
					"avg": 823,
					"count": 1,
					"min": 823,
					"max": 823
				},
				"2024-08-04": {
					"avg": 720,
					"count": 1,
					"min": 720,
					"max": 720
				},
				"2024-08-20": {
					"avg": 719,
					"count": 1,
					"min": 719,
					"max": 719
				},
				"2024-09-05": {
					"avg": 894,
					"count": 1,
					"min": 894,
					"max": 894
				},
				"2024-09-15": {
					"avg": 818,
					"count": 1,
					"min": 818,
					"max": 818
				}
			},
			"avg": 612,
			"avg7": 832,
			"avg28": 832
		},
		"holo-nearmint": {
			"history": {
				"2024-05-31": {
					"avg": 1002,
					"count": 2,
					"min": 769,
					"max": 1234
				},
				"2024-06-01": {
					"avg": 1198,
					"count": 1,
					"min": 1198,
					"max": 1198
				},
				"2024-06-03": {
					"avg": 1234,
					"count": 1,
					"min": 1234,
					"max": 1234
				},
				"2024-06-10": {
					"avg": 1216,
					"count": 2,
					"min": 1198,
					"max": 1234
				},
				"2024-06-12": {
					"avg": 1234,
					"count": 1,
					"min": 1234,
					"max": 1234
				},
				"2024-06-19": {
					"avg": 1198,
					"count": 1,
					"min": 1198,
					"max": 1198
				},
				"2024-07-17": {
					"avg": 2198,
					"count": 1,
					"min": 2198,
					"max": 2198
				},
				"2024-07-20": {
					"avg": 1233,
					"count": 1,
					"min": 1233,
					"max": 1233
				},
				"2024-08-27": {
					"avg": 797,
					"count": 1,
					"min": 797,
					"max": 797
				},
				"2024-09-03": {
					"avg": 1028,
					"count": 1,
					"min": 1028,
					"max": 1028
				},
				"2024-09-11": {
					"avg": 960,
					"count": 1,
					"min": 960,
					"max": 960
				},
				"2024-09-14": {
					"avg": 874,
					"count": 1,
					"min": 874,
					"max": 874
				},
				"2024-09-19": {
					"avg": 1022,
					"count": 4,
					"min": 1022,
					"max": 1022
				},
				"2024-09-23": {
					"avg": 897,
					"count": 2,
					"min": 896,
					"max": 897
				}
			},
			"avg": 1114,
			"avg7": -1,
			"avg28": -1
		},
		"holo-played": {
			"history": {
				"2024-06-11": {
					"avg": 697,
					"count": 1,
					"min": 697,
					"max": 697
				},
				"2024-06-18": {
					"avg": 697,
					"count": 6,
					"min": 697,
					"max": 697
				},
				"2024-08-16": {
					"avg": 650,
					"count": 1,
					"min": 650,
					"max": 650
				},
				"2024-09-03": {
					"avg": 1017,
					"count": 1,
					"min": 1017,
					"max": 1017
				},
				"2024-09-09": {
					"avg": 661,
					"count": 1,
					"min": 661,
					"max": 661
				},
				"2024-09-11": {
					"avg": 661,
					"count": 2,
					"min": 661,
					"max": 661
				}
			},
			"avg": 711,
			"avg7": -1,
			"avg28": -1
		}
	}
}