{
    "data": {
        "holo": {
            "history": {
                "2024-05-17": {
                    "avg": 2.238387096774194,
                    "count": 31,
                    "min": 1.22,
                    "max": 5.23
                },
                "2024-05-16": {
                    "avg": 2.29,
                    "count": 2,
                    "min": 2.12,
                    "max": 2.46
                },
                "2024-05-18": {
                    "avg": 2.44125,
                    "count": 8,
                    "min": 1.23,
                    "max": 5.23
                },
                "2024-05-19": {
                    "avg": 2.52,
                    "count": 3,
                    "min": 1.4,
                    "max": 3.17
                }
            },
            "avg": 2.44125,
            "avg7": 2.280487804878049,
            "avg28": 2.280487804878049
        }
    }
}