{
    "data": {
        "holo": {
            "history": {
                "2022-12-11": {
                    "avg": 9.735,
                    "count": 2,
                    "min": 8.48,
                    "max": 10.99
                },
                "2022-12-14": {
                    "avg": 8.665,
                    "count": 2,
                    "min": 8.65,
                    "max": 8.68
                }
            },
            "avg": 8.665,
            "avg7": 9.2,
            "avg28": 9.2
        }
    }
}