{
	"data": {
		"holo-good": {
			"history": {
				"2022-11-12": {
					"avg": 1699,
					"count": 1
				},
				"2022-12-09": {
					"avg": 1655,
					"count": 1,
					"min": 1655,
					"max": 1655
				},
				"2022-12-13": {
					"avg": 1798,
					"count": 1,
					"min": 1798,
					"max": 1798
				},
				"2022-12-16": {
					"avg": 1899,
					"count": 1,
					"min": 1899,
					"max": 1899
				},
				"2023-02-12": {
					"avg": 1899,
					"count": 1,
					"min": 1899,
					"max": 1899
				},
				"2023-03-18": {
					"avg": 1731,
					"count": 1,
					"min": 1731,
					"max": 1731
				},
				"2023-04-11": {
					"avg": 1647,
					"count": 2,
					"min": 1594,
					"max": 1699
				},
				"2023-04-13": {
					"avg": 2290,
					"count": 1,
					"min": 2290,
					"max": 2290
				},
				"2023-04-20": {
					"avg": 1675,
					"count": 1,
					"min": 1675,
					"max": 1675
				},
				"2023-05-09": {
					"avg": 2299,
					"count": 1,
					"min": 2299,
					"max": 2299
				},
				"2023-05-11": {
					"avg": 1700,
					"count": 1,
					"min": 1700,
					"max": 1700
				},
				"2023-05-26": {
					"avg": 1500,
					"count": 1,
					"min": 1500,
					"max": 1500
				},
				"2023-06-24": {
					"avg": 2356,
					"count": 2,
					"min": 1931,
					"max": 2781
				},
				"2023-06-30": {
					"avg": 1636,
					"count": 1,
					"min": 1636,
					"max": 1636
				},
				"2023-07-28": {
					"avg": 10579,
					"count": 1,
					"min": 10579,
					"max": 10579
				},
				"2023-09-15": {
					"avg": 1200,
					"count": 1,
					"min": 1200,
					"max": 1200
				},
				"2023-09-16": {
					"avg": 2063,
					"count": 2,
					"min": 1927,
					"max": 2198
				},
				"2023-10-26": {
					"avg": 1699,
					"count": 1,
					"min": 1699,
					"max": 1699
				},
				"2023-11-27": {
					"avg": 2199,
					"count": 1,
					"min": 2199,
					"max": 2199
				},
				"2024-05-20": {
					"avg": 2400,
					"count": 1,
					"min": 2400,
					"max": 2400
				},
				"2024-08-16": {
					"avg": 2299,
					"count": 1,
					"min": 2299,
					"max": 2299
				},
				"2024-09-06": {
					"avg": 1992,
					"count": 1,
					"min": 1992,
					"max": 1992
				},
				"2024-09-10": {
					"avg": 3975,
					"count": 1,
					"min": 3975,
					"max": 3975
				}
			},
			"avg": 2318,
			"avg7": 2199,
			"avg28": 2199
		},
		"holo-nearmint": {
			"history": {
				"2024-05-31": {
					"avg": 2382,
					"count": 1,
					"min": 2382,
					"max": 2382
				},
				"2024-06-03": {
					"avg": 2559,
					"count": 1,
					"min": 2559,
					"max": 2559
				},
				"2024-06-06": {
					"avg": 2298,
					"count": 1,
					"min": 2298,
					"max": 2298
				},
				"2024-06-13": {
					"avg": 2275,
					"count": 1,
					"min": 2275,
					"max": 2275
				},
				"2024-06-19": {
					"avg": 2295,
					"count": 1,
					"min": 2295,
					"max": 2295
				},
				"2024-06-25": {
					"avg": 2658,
					"count": 1,
					"min": 2658,
					"max": 2658
				},
				"2024-06-27": {
					"avg": 2395,
					"count": 1,
					"min": 2395,
					"max": 2395
				},
				"2024-06-28": {
					"avg": 2425,
					"count": 1,
					"min": 2425,
					"max": 2425
				},
				"2024-06-29": {
					"avg": 2658,
					"count": 1,
					"min": 2658,
					"max": 2658
				},
				"2024-07-01": {
					"avg": 2350,
					"count": 1,
					"min": 2350,
					"max": 2350
				},
				"2024-07-11": {
					"avg": 2728,
					"count": 2,
					"min": 2599,
					"max": 2856
				},
				"2024-07-17": {
					"avg": 2390,
					"count": 1,
					"min": 2390,
					"max": 2390
				},
				"2024-07-31": {
					"avg": 2389,
					"count": 1,
					"min": 2389,
					"max": 2389
				},
				"2024-08-05": {
					"avg": 2500,
					"count": 1,
					"min": 2500,
					"max": 2500
				},
				"2024-08-19": {
					"avg": 2390,
					"count": 1,
					"min": 2390,
					"max": 2390
				},
				"2024-08-20": {
					"avg": 2495,
					"count": 2,
					"min": 2399,
					"max": 2590
				},
				"2024-08-21": {
					"avg": 2799,
					"count": 1,
					"min": 2799,
					"max": 2799
				},
				"2024-08-31": {
					"avg": 1999,
					"count": 1,
					"min": 1999,
					"max": 1999
				}
			},
			"avg": 2460,
			"avg7": -1,
			"avg28": -1
		}
	}
}