{
    "data": {
        "holo": {
            "history": {
                "2022-12-09": {
                    "avg": 7.49,
                    "count": 1,
                    "min": 7.49,
                    "max": 7.49
                },
                "2022-12-16": {
                    "avg": 12.866666666666665,
                    "count": 3,
                    "min": 5.64,
                    "max": 16.48
                }
            },
            "avg": 12.866666666666665,
            "avg7": 11.522499999999999,
            "avg28": 11.522499999999999
        }
    }
}